CHANGES.rst
CONTRIBUTORS.rst
MANIFEST.in
README.rst
setup.cfg
setup.py
docs/LICENSE.GPL
docs/LICENSE.rst
docs/index.rst
src/collective/__init__.py
src/collective.archetypes.select2.egg-info/PKG-INFO
src/collective.archetypes.select2.egg-info/SOURCES.txt
src/collective.archetypes.select2.egg-info/dependency_links.txt
src/collective.archetypes.select2.egg-info/entry_points.txt
src/collective.archetypes.select2.egg-info/namespace_packages.txt
src/collective.archetypes.select2.egg-info/not-zip-safe
src/collective.archetypes.select2.egg-info/requires.txt
src/collective.archetypes.select2.egg-info/top_level.txt
src/collective/archetypes/__init__.py
src/collective/archetypes/select2/__init__.py
src/collective/archetypes/select2/base.py
src/collective/archetypes/select2/configure.zcml
src/collective/archetypes/select2/interfaces.py
src/collective/archetypes/select2/select2widget.py
src/collective/archetypes/select2/setuphandlers.py
src/collective/archetypes/select2/testing.py
src/collective/archetypes/select2/utils.py
src/collective/archetypes/select2/browser/__init__.py
src/collective/archetypes/select2/browser/configure.zcml
src/collective/archetypes/select2/browser/patterns_widget.pt
src/collective/archetypes/select2/browser/widget.py
src/collective/archetypes/select2/browser/overrides/.gitkeep
src/collective/archetypes/select2/browser/static/.gitkeep
src/collective/archetypes/select2/locales/collective.archetypes.select2.pot
src/collective/archetypes/select2/locales/update.sh
src/collective/archetypes/select2/profiles/default/browserlayer.xml
src/collective/archetypes/select2/profiles/default/cssregistry.xml
src/collective/archetypes/select2/profiles/default/jsregistry.xml
src/collective/archetypes/select2/profiles/default/metadata.xml
src/collective/archetypes/select2/profiles/default/registry.xml
src/collective/archetypes/select2/profiles/uninstall/browserlayer.xml
src/collective/archetypes/select2/static/select2.js
src/collective/archetypes/select2/static/select2.min.css
src/collective/archetypes/select2/static/widgets-select2-select2-spinner.gif
src/collective/archetypes/select2/static/widgets-select2-select2.png
src/collective/archetypes/select2/static/widgets-select2-select2x2.png
src/collective/archetypes/select2/tests/__init__.py
src/collective/archetypes/select2/tests/test_robot.py
src/collective/archetypes/select2/tests/test_setup.py
src/collective/archetypes/select2/tests/robot/test_example.robot